[{"language":"C","value":333818665508},{"language":"C++","value":53711761310},{"language":"PHP","value":44823998810},{"language":"JavaScript","value":43248801182},{"language":"Java","value":37601164280},{"language":"Ruby","value":24469058776},{"language":"Python","value":21019531045},{"language":"C#","value":17461474774},{"language":"Erlang","value":9409620101},{"language":"HTML","value":7945747249},{"language":"Perl","value":7637430855},{"language":"Emacs Lisp","value":7207826470},{"language":"Objective-C","value":4885974719},{"language":"Shell","value":3970400012},{"language":"Assembly","value":2883491233},{"language":"VimL","value":2289849461},{"language":"Objective-J","value":1655370947},{"language":"ActionScript","value":1562936026},{"language":"ASP","value":1480085912},{"language":"CSS","value":1190353367},{"language":"Lua","value":1064192584},{"language":"Vim script","value":1029838997},{"language":"Fortran","value":942700475},{"language":"Common Lisp","value":938138381},{"language":"D","value":926980728},{"language":"Scala","value":817162440},{"language":"TypeScript","value":738435013},{"language":"Pascal","value":666422550},{"language":"OCaml","value":636855861},{"language":"Scilab","value":586712813},{"language":"Prolog","value":552573186},{"language":"Ada","value":550249209},{"language":"Groovy","value":541054816},{"language":"Haskell","value":500587801},{"language":"Scheme","value":486613393},{"language":"Clojure","value":439939203},{"language":"TeX","value":428427144},{"language":"Makefile","value":414829610},{"language":"Tcl","value":412564716},{"language":"XSLT","value":401935522},{"language":"Racket","value":394200346},{"language":"R","value":392330856},{"language":"Max","value":379585585},{"language":"Eiffel","value":379019294},{"language":"Visual Basic","value":363957809},{"language":"Roff","value":360468848},{"language":"Jupyter Notebook","value":248295590},{"language":"Verilog","value":246505047},{"language":"LLVM","value":243794082},{"language":"Rust","value":219864829},{"language":"Go","value":211712088},{"language":"ColdFusion","value":210669637},{"language":"VHDL","value":207316091},{"language":"Factor","value":181033748},{"language":"Mathematica","value":180483380},{"language":"PLpgSQL","value":165553595},{"language":"Dylan","value":164820536},{"language":"Logos","value":140272426},{"language":"F#","value":138506422},{"language":"Matlab","value":138479787},{"language":"Processing","value":137788004},{"language":"Parrot","value":133383295},{"language":"PostScript","value":132056838},{"language":"Groff","value":128844487},{"language":"CMake","value":115832847},{"language":"Self","value":100302364},{"language":"Pure Data","value":98975122},{"language":"Web Ontology Language","value":96477749},{"language":"GAP","value":92439362},{"language":"SuperCollider","value":91878888},{"language":"GLSL","value":86627859},{"language":"Io","value":86277188},{"language":"Smalltalk","value":86115762},{"language":"CoffeeScript","value":81802750},{"language":"Standard ML","value":73495726},{"language":"Gherkin","value":69382201},{"language":"SQLPL","value":63572232},{"language":"OpenEdge ABL","value":63159493},{"language":"AGS Script","value":61749698},{"language":"Haxe","value":59503508},{"language":"M4","value":58254320},{"language":"Smarty","value":54085913},{"language":"Objective-C++","value":48956247},{"language":"Perl6","value":46703196},{"language":"Eagle","value":45369784},{"language":"XML","value":40922568},{"language":"Perl 6","value":38007230},{"language":"Coq","value":37338692},{"language":"Nim","value":34643372},{"language":"PLSQL","value":34099681},{"language":"LilyPond","value":33308873},{"language":"Yacc","value":32832074},{"language":"Harbour","value":31736049},{"language":"Puppet","value":29061024},{"language":"Arc","value":28914563},{"language":"Boo","value":28097247},{"language":"Nemerle","value":27187972},{"language":"PowerShell","value":26643660},{"language":"Cucumber","value":24826899},{"language":"GCC Machine Description","value":21881070},{"language":"Nit","value":21561664},{"language":"AMPL","value":21209411},{"language":"Diff","value":19466692},{"language":"Cuda","value":18432726},{"language":"SQL","value":17736575},{"language":"Dart","value":16959734},{"language":"DTrace","value":16800857},{"language":"nesC","value":16338158},{"language":"Batchfile","value":16263683},{"language":"AutoHotkey","value":15698438},{"language":"QML","value":15451299},{"language":"KiCad","value":15190509},{"language":"Mako","value":14998390},{"language":"ooc","value":14862583},{"language":"Awk","value":14714501},{"language":"Gettext Catalog","value":14487898},{"language":"Vala","value":14360415},{"language":"Component Pascal","value":13841980},{"language":"ATS","value":13511501},{"language":"XProc","value":13497232},{"language":"XQuery","value":13155362},{"language":"SourcePawn","value":12956349},{"language":"Forth","value":12665066},{"language":"Arduino","value":12215645},{"language":"ChucK","value":12095509},{"language":"Lex","value":11040258},{"language":"eC","value":10952953},{"language":"Elixir","value":10571167},{"language":"FLUX","value":10406148},{"language":"Nu","value":9981967},{"language":"COBOL","value":9930260},{"language":"Pike","value":9677012},{"language":"XS","value":9482632},{"language":"Oz","value":9288362},{"language":"Hack","value":9270756},{"language":"Julia","value":8810328},{"language":"xBase","value":8549527},{"language":"AutoIt","value":8013163},{"language":"NSIS","value":7942487},{"language":"FreeMarker","value":7657107},{"language":"M","value":7647825},{"language":"ApacheConf","value":7615852},{"language":"BitBake","value":7448434},{"language":"BlitzBasic","value":7317353},{"language":"Swift","value":7270077},{"language":"DIGITAL Command Language","value":7113423},{"language":"Ragel in Ruby Host","value":6854190},{"language":"Bison","value":6784519},{"language":"Game Maker Language","value":6564214},{"language":"E","value":6225748},{"language":"Xtend","value":6091293},{"language":"Gosu","value":5453442},{"language":"Rebol","value":5371261},{"language":"SAS","value":5175499},{"language":"IDL","value":5123629},{"language":"Ceylon","value":5003992},{"language":"Red","value":4450720},{"language":"Xojo","value":4341197},{"language":"Terra","value":4304858},{"language":"Mirah","value":4124817},{"language":"Opa","value":4081792},{"language":"Augeas","value":3875315},{"language":"QMake","value":3776294},{"language":"HCL","value":3766474},{"language":"Gnuplot","value":3618631},{"language":"Graphviz (DOT)","value":3533803},{"language":"SystemVerilog","value":3441526},{"language":"Protocol Buffer","value":3282745},{"language":"XC","value":2917647},{"language":"REALbasic","value":2806572},{"language":"J","value":2739915},{"language":"Slash","value":2707861},{"language":"AppleScript","value":2678502},{"language":"POV-Ray SDL","value":2531361},{"language":"CLIPS","value":2457131},{"language":"Turing","value":2392966},{"language":"KiCad Layout","value":2382233},{"language":"Apex","value":2372504},{"language":"VCL","value":2334357},{"language":"Agda","value":2322469},{"language":"Kotlin","value":2309167},{"language":"Lasso","value":2050769},{"language":"Bluespec","value":2026940},{"language":"LiveScript","value":1963634},{"language":"Thrift","value":1779974},{"language":"Ioke","value":1754078},{"language":"BlitzMax","value":1721988},{"language":"NewLisp","value":1643347},{"language":"IGOR Pro","value":1570938},{"language":"HLSL","value":1520916},{"language":"Logtalk","value":1500694},{"language":"MAXScript","value":1485997},{"language":"Ragel","value":1403705},{"language":"MTML","value":1302508},{"language":"Inno Setup","value":1266227},{"language":"OpenSCAD","value":1264757},{"language":"1C Enterprise","value":1181052},{"language":"UnrealScript","value":1037492},{"language":"EmberScript","value":988996},{"language":"Fancy","value":988344},{"language":"GDB","value":962929},{"language":"Limbo","value":898427},{"language":"Module Management System","value":893015},{"language":"AspectJ","value":877426},{"language":"Stan","value":875966},{"language":"Mercury","value":756567},{"language":"Csound Score","value":739730},{"language":"SRecode Template","value":648833},{"language":"ANTLR","value":645608},{"language":"Elm","value":628209},{"language":"Squirrel","value":600722},{"language":"Nginx","value":586655},{"language":"MoonScript","value":567986},{"language":"Clean","value":533195},{"language":"Frege","value":503623},{"language":"Brightscript","value":448026},{"language":"Nix","value":423522},{"language":"Crystal","value":395643},{"language":"Liquid","value":387943},{"language":"RenderScript","value":369557},{"language":"Vue","value":337275},{"language":"RAML","value":319663},{"language":"Clarion","value":319639},{"language":"Bro","value":313924},{"language":"MQL4","value":296224},{"language":"Brainfuck","value":261160},{"language":"LSL","value":254780},{"language":"Alloy","value":249002},{"language":"Genshi","value":236863},{"language":"PigLatin","value":231532},{"language":"CartoCSS","value":228416},{"language":"Oxygene","value":222002},{"language":"SaltStack","value":205907},{"language":"RobotFramework","value":205117},{"language":"AngelScript","value":202326},{"language":"Stata","value":198641},{"language":"GDScript","value":165854},{"language":"Pep8","value":140064},{"language":"Isabelle","value":139764},{"language":"TXL","value":139717},{"language":"Jasmin","value":127841},{"language":"Click","value":126899},{"language":"Rascal","value":119898},{"language":"Handlebars","value":97552},{"language":"Kit","value":97365},{"language":"LOLCODE","value":86207},{"language":"Inform 7","value":82561},{"language":"Idris","value":81474},{"language":"Rouge","value":78213},{"language":"Cool","value":76275},{"language":"CWeb","value":74764},{"language":"ShaderLab","value":69230},{"language":"Mask","value":67950},{"language":"Meson","value":63133},{"language":"Csound Document","value":53526},{"language":"KRL","value":49817},{"language":"NetLogo","value":48370},{"language":"REXX","value":48348},{"language":"PicoLisp","value":47991},{"language":"Modula-2","value":40784},{"language":"PAWN","value":36645},{"language":"ABAP","value":34585},{"language":"API Blueprint","value":34290},{"language":"mupad","value":33819},{"language":"APL","value":26817},{"language":"WebAssembly","value":25785},{"language":"DM","value":24011},{"language":"GAMS","value":20076},{"language":"Pan","value":18647},{"language":"MQL5","value":18609},{"language":"Smali","value":17574},{"language":"NCL","value":16913},{"language":"Csound","value":16205},{"language":"EQ","value":15158},{"language":"Monkey","value":13290},{"language":"JFlex","value":12832},{"language":"Redcode","value":10861},{"language":"Metal","value":10480},{"language":"PureScript","value":10292},{"language":"Hy","value":6672},{"language":"Pony","value":5456},{"language":"Myghty","value":5328},{"language":"Fantom","value":5249},{"language":"Grace","value":3614},{"language":"SMT","value":2550},{"language":"Jolie","value":2390},{"language":"ECL","value":2205},{"language":"Filebench WML","value":1501},{"language":"Modelica","value":1482},{"language":"Grammatical Framework","value":1478},{"language":"PowerBuilder","value":1344},{"language":"Cirru","value":1040},{"language":"Tea","value":792},{"language":"Cap'n Proto","value":652},{"language":"Zephir","value":467},{"language":"PureBasic","value":240},{"language":"Omgrofl","value":239},{"language":"wisp","value":162},{"language":"JSONiq","value":126},{"language":"Dogescript","value":92},{"language":"Golo","value":72},{"language":"Chapel","value":39},{"language":"Genie","value":22},{"language":"Shen","value":19},{"language":"Cycript","value":9}]