[{"language":"C","value":323612025528},{"language":"C++","value":51829712947},{"language":"PHP","value":43212064102},{"language":"JavaScript","value":41739971859},{"language":"Java","value":36726789950},{"language":"Ruby","value":23787467847},{"language":"Python","value":20461423605},{"language":"C#","value":17258469182},{"language":"Erlang","value":9265929036},{"language":"HTML","value":7879954008},{"language":"Perl","value":7486451840},{"language":"Emacs Lisp","value":7038155107},{"language":"Objective-C","value":4727670207},{"language":"Shell","value":3811493503},{"language":"Assembly","value":2716945928},{"language":"VimL","value":2289849461},{"language":"Objective-J","value":1637175285},{"language":"ActionScript","value":1526279678},{"language":"ASP","value":1475145626},{"language":"CSS","value":1151311605},{"language":"Lua","value":1049672084},{"language":"Fortran","value":921053844},{"language":"Common Lisp","value":920973786},{"language":"D","value":875377869},{"language":"Vim script","value":854144185},{"language":"Scala","value":802207937},{"language":"TypeScript","value":725282510},{"language":"Pascal","value":655761789},{"language":"OCaml","value":633757322},{"language":"Prolog","value":551489429},{"language":"Ada","value":548255916},{"language":"Groovy","value":505848626},{"language":"Scheme","value":483811353},{"language":"Haskell","value":469179160},{"language":"Clojure","value":437730632},{"language":"TeX","value":412979196},{"language":"Makefile","value":408918667},{"language":"Tcl","value":408052369},{"language":"XSLT","value":391637789},{"language":"R","value":387979357},{"language":"Max","value":379585585},{"language":"Eiffel","value":378424346},{"language":"Roff","value":360109372},{"language":"Racket","value":354336305},{"language":"Visual Basic","value":282953931},{"language":"Jupyter Notebook","value":246926140},{"language":"Verilog","value":246024222},{"language":"LLVM","value":243792154},{"language":"Rust","value":214386764},{"language":"Go","value":208387812},{"language":"ColdFusion","value":206402986},{"language":"VHDL","value":201897539},{"language":"Factor","value":180986286},{"language":"Mathematica","value":180440236},{"language":"Dylan","value":164818024},{"language":"PLpgSQL","value":164762988},{"language":"Logos","value":140204098},{"language":"F#","value":137813665},{"language":"Processing","value":136910550},{"language":"Matlab","value":134969282},{"language":"Parrot","value":129636016},{"language":"PostScript","value":129237149},{"language":"Groff","value":128632088},{"language":"CMake","value":113600564},{"language":"Self","value":100302364},{"language":"Pure Data","value":98969649},{"language":"Web Ontology Language","value":96223139},{"language":"GAP","value":92390115},{"language":"SuperCollider","value":91634421},{"language":"GLSL","value":86334894},{"language":"Smalltalk","value":85876371},{"language":"Io","value":82417313},{"language":"CoffeeScript","value":76673490},{"language":"Standard ML","value":73493622},{"language":"Gherkin","value":63982001},{"language":"SQLPL","value":63553427},{"language":"AGS Script","value":61748207},{"language":"OpenEdge ABL","value":60832118},{"language":"M4","value":57235416},{"language":"Haxe","value":56607460},{"language":"Smarty","value":53240356},{"language":"Perl6","value":46703196},{"language":"Objective-C++","value":45998647},{"language":"Eagle","value":45369784},{"language":"XML","value":40760494},{"language":"Perl 6","value":37519252},{"language":"Coq","value":37229420},{"language":"Nim","value":34642473},{"language":"LilyPond","value":33308826},{"language":"Yacc","value":32231423},{"language":"PLSQL","value":32040462},{"language":"Harbour","value":31736049},{"language":"Arc","value":28914563},{"language":"Puppet","value":28531214},{"language":"Boo","value":27894308},{"language":"Nemerle","value":26890293},{"language":"PowerShell","value":25694431},{"language":"Cucumber","value":24826899},{"language":"GCC Machine Description","value":21881070},{"language":"Nit","value":21561664},{"language":"AMPL","value":21209411},{"language":"Diff","value":19466692},{"language":"Scilab","value":19023136},{"language":"SQL","value":17736575},{"language":"Dart","value":16959656},{"language":"DTrace","value":16696093},{"language":"nesC","value":16338158},{"language":"Cuda","value":16097817},{"language":"Batchfile","value":15909130},{"language":"AutoHotkey","value":15358452},{"language":"QML","value":15276757},{"language":"KiCad","value":15190509},{"language":"Mako","value":14997978},{"language":"ooc","value":14862421},{"language":"Awk","value":14520917},{"language":"Gettext Catalog","value":14487898},{"language":"Vala","value":13511901},{"language":"ATS","value":13511501},{"language":"XProc","value":13465674},{"language":"Component Pascal","value":13346669},{"language":"XQuery","value":13039118},{"language":"SourcePawn","value":12902857},{"language":"ChucK","value":12095509},{"language":"Forth","value":11879135},{"language":"Arduino","value":11715404},{"language":"eC","value":10932349},{"language":"Lex","value":10833430},{"language":"Elixir","value":10528394},{"language":"FLUX","value":10375963},{"language":"Nu","value":9959697},{"language":"COBOL","value":9920653},{"language":"Pike","value":9649212},{"language":"XS","value":9451561},{"language":"Oz","value":9288362},{"language":"Hack","value":9251699},{"language":"Julia","value":8808333},{"language":"xBase","value":8549527},{"language":"AutoIt","value":8013163},{"language":"NSIS","value":7798654},{"language":"FreeMarker","value":7620066},{"language":"M","value":7486849},{"language":"ApacheConf","value":7459497},{"language":"BitBake","value":7448434},{"language":"BlitzBasic","value":7202181},{"language":"DIGITAL Command Language","value":7112817},{"language":"Bison","value":6710137},{"language":"Game Maker Language","value":6564214},{"language":"E","value":6206678},{"language":"Swift","value":6174254},{"language":"Ragel in Ruby Host","value":6120800},{"language":"Xtend","value":6091293},{"language":"Gosu","value":5416815},{"language":"Rebol","value":5371060},{"language":"SAS","value":5160032},{"language":"IDL","value":5119430},{"language":"Ceylon","value":5003992},{"language":"Red","value":4450720},{"language":"Xojo","value":4341197},{"language":"Terra","value":4278374},{"language":"Mirah","value":4114385},{"language":"Opa","value":4081792},{"language":"Augeas","value":3875315},{"language":"HCL","value":3764017},{"language":"Gnuplot","value":3600258},{"language":"QMake","value":3571918},{"language":"Graphviz (DOT)","value":3513744},{"language":"SystemVerilog","value":3413728},{"language":"Protocol Buffer","value":3278135},{"language":"XC","value":2815078},{"language":"REALbasic","value":2806572},{"language":"J","value":2739915},{"language":"Slash","value":2707861},{"language":"AppleScript","value":2653103},{"language":"POV-Ray SDL","value":2531361},{"language":"CLIPS","value":2332337},{"language":"VCL","value":2332156},{"language":"Agda","value":2322469},{"language":"Kotlin","value":2270449},{"language":"Lasso","value":2045970},{"language":"Bluespec","value":2026940},{"language":"LiveScript","value":1957505},{"language":"Apex","value":1883681},{"language":"Thrift","value":1779602},{"language":"Ioke","value":1754054},{"language":"BlitzMax","value":1721988},{"language":"KiCad Layout","value":1690296},{"language":"NewLisp","value":1643255},{"language":"IGOR Pro","value":1570938},{"language":"Logtalk","value":1500694},{"language":"HLSL","value":1424933},{"language":"MAXScript","value":1410503},{"language":"Ragel","value":1403705},{"language":"MTML","value":1302508},{"language":"Inno Setup","value":1236655},{"language":"OpenSCAD","value":1230817},{"language":"1C Enterprise","value":1181052},{"language":"Turing","value":1159910},{"language":"UnrealScript","value":1026936},{"language":"EmberScript","value":988996},{"language":"Fancy","value":981939},{"language":"GDB","value":959865},{"language":"Limbo","value":898427},{"language":"Module Management System","value":893015},{"language":"Stan","value":875966},{"language":"Mercury","value":755345},{"language":"Csound Score","value":739730},{"language":"AspectJ","value":678766},{"language":"SRecode Template","value":647527},{"language":"ANTLR","value":645608},{"language":"Elm","value":628209},{"language":"Squirrel","value":600722},{"language":"Nginx","value":568297},{"language":"MoonScript","value":567986},{"language":"Clean","value":511168},{"language":"Frege","value":503623},{"language":"Brightscript","value":448026},{"language":"Nix","value":421831},{"language":"Crystal","value":395440},{"language":"Liquid","value":387943},{"language":"RenderScript","value":369302},{"language":"Vue","value":320712},{"language":"RAML","value":319663},{"language":"Clarion","value":319639},{"language":"Bro","value":313924},{"language":"MQL4","value":296224},{"language":"Brainfuck","value":261106},{"language":"Alloy","value":249002},{"language":"Genshi","value":236863},{"language":"PigLatin","value":231532},{"language":"CartoCSS","value":228416},{"language":"Oxygene","value":222002},{"language":"SaltStack","value":205907},{"language":"RobotFramework","value":204520},{"language":"AngelScript","value":202326},{"language":"Stata","value":198641},{"language":"GDScript","value":165854},{"language":"Pep8","value":140064},{"language":"Isabelle","value":139764},{"language":"TXL","value":139717},{"language":"Jasmin","value":127841},{"language":"Click","value":126899},{"language":"Rascal","value":119898},{"language":"LSL","value":107951},{"language":"Handlebars","value":97552},{"language":"Kit","value":97365},{"language":"LOLCODE","value":86207},{"language":"Inform 7","value":82561},{"language":"Idris","value":81008},{"language":"Rouge","value":78213},{"language":"Cool","value":76275},{"language":"CWeb","value":74764},{"language":"ShaderLab","value":69230},{"language":"Mask","value":67619},{"language":"Meson","value":62264},{"language":"Csound Document","value":53526},{"language":"KRL","value":49817},{"language":"NetLogo","value":48370},{"language":"REXX","value":48348},{"language":"PicoLisp","value":47991},{"language":"Modula-2","value":40784},{"language":"ABAP","value":34585},{"language":"PAWN","value":34466},{"language":"API Blueprint","value":29130},{"language":"WebAssembly","value":25785},{"language":"mupad","value":25037},{"language":"DM","value":24011},{"language":"GAMS","value":20076},{"language":"Pan","value":18647},{"language":"MQL5","value":18609},{"language":"Smali","value":17574},{"language":"NCL","value":16340},{"language":"Csound","value":16205},{"language":"EQ","value":15158},{"language":"Monkey","value":13290},{"language":"JFlex","value":12832},{"language":"Redcode","value":10861},{"language":"Metal","value":10480},{"language":"PureScript","value":10087},{"language":"Hy","value":6672},{"language":"Pony","value":5456},{"language":"Myghty","value":5328},{"language":"Fantom","value":5249},{"language":"Grace","value":3614},{"language":"SMT","value":2550},{"language":"Jolie","value":2390},{"language":"ECL","value":2205},{"language":"Filebench WML","value":1501},{"language":"Modelica","value":1482},{"language":"Grammatical Framework","value":1478},{"language":"PowerBuilder","value":1344},{"language":"Cirru","value":1040},{"language":"Tea","value":792},{"language":"Cap'n Proto","value":652},{"language":"Zephir","value":467},{"language":"PureBasic","value":240},{"language":"Omgrofl","value":239},{"language":"wisp","value":162},{"language":"JSONiq","value":126},{"language":"Dogescript","value":92},{"language":"Golo","value":72},{"language":"APL","value":58},{"language":"Chapel","value":39},{"language":"Genie","value":22},{"language":"Shen","value":19},{"language":"Cycript","value":9}]